pipfreeze.py
pipfreeze-2.0.3.dist-info/LICENSE
pipfreeze-2.0.3.dist-info/METADATA
pipfreeze-2.0.3.dist-info/WHEEL
pipfreeze-2.0.3.dist-info/entry_points.txt
pipfreeze-2.0.3.dist-info/top_level.txt
pipfreeze-2.0.3.dist-info/RECORD
