Metadata-Version: 2.1
Name: pipfreeze
Version: 2.0.3
Summary: Tool to produce better formatted pip freeze.
Home-page: https://github.com/earthastronaut/pipfreeze
Author: Dylan Gregersen
Author-email: an.email0101@gmail.com
License: MIT
Platform: UNKNOWN
Classifier: Intended Audience :: Developers
Classifier: License :: OSI Approved :: MIT License
Classifier: Programming Language :: Python
Classifier: Programming Language :: Python :: 3
Requires-Python: >=2.7
